[{"heart_rate":90.0,"start_time":1724699671049},{"heart_rate":92.0,"start_time":1724699672054},{"heart_rate":93.0,"start_time":1724699673061},{"heart_rate":95.0,"start_time":1724699674066},{"heart_rate":95.0,"start_time":1724699675072},{"heart_rate":94.0,"start_time":1724699676078},{"heart_rate":93.0,"start_time":1724699677082},{"heart_rate":93.0,"start_time":1724699678087},{"heart_rate":94.0,"start_time":1724699679092},{"heart_rate":95.0,"start_time":1724699680096},{"heart_rate":96.0,"start_time":1724699681101},{"heart_rate":96.0,"start_time":1724699682107},{"heart_rate":96.0,"start_time":1724699683111},{"heart_rate":97.0,"start_time":1724699684115},{"heart_rate":97.0,"start_time":1724699685120},{"heart_rate":98.0,"start_time":1724699686124},{"heart_rate":99.0,"start_time":1724699687150},{"heart_rate":99.0,"start_time":1724699688150},{"heart_rate":99.0,"start_time":1724699689150},{"heart_rate":99.0,"start_time":1724699690150},{"heart_rate":99.0,"start_time":1724699691150},{"heart_rate":99.0,"start_time":1724699692150},{"heart_rate":100.0,"start_time":1724699693150},{"heart_rate":100.0,"start_time":1724699694150},{"heart_rate":101.0,"start_time":1724699695150},{"heart_rate":101.0,"start_time":1724699696150},{"heart_rate":101.0,"start_time":1724699697150},{"heart_rate":102.0,"start_time":1724699698150},{"heart_rate":102.0,"start_time":1724699699150},{"heart_rate":103.0,"start_time":1724699700150},{"heart_rate":104.0,"start_time":1724699704361},{"heart_rate":104.0,"start_time":1724699705361},{"heart_rate":104.0,"start_time":1724699706361},{"heart_rate":104.0,"start_time":1724699707361},{"heart_rate":104.0,"start_time":1724699708361},{"heart_rate":104.0,"start_time":1724699709361},{"heart_rate":104.0,"start_time":1724699710361},{"heart_rate":104.0,"start_time":1724699711361},{"heart_rate":104.0,"start_time":1724699712361},{"heart_rate":104.0,"start_time":1724699713361},{"heart_rate":104.0,"start_time":1724699714361},{"heart_rate":103.0,"start_time":1724699715361},{"heart_rate":102.0,"start_time":1724699716361},{"heart_rate":101.0,"start_time":1724699717361},{"heart_rate":101.0,"start_time":1724699718361},{"heart_rate":101.0,"start_time":1724699719361},{"heart_rate":102.0,"start_time":1724699720361},{"heart_rate":102.0,"start_time":1724699721361},{"heart_rate":102.0,"start_time":1724699722361},{"heart_rate":102.0,"start_time":1724699723361},{"heart_rate":102.0,"start_time":1724699724361},{"heart_rate":101.0,"start_time":1724699725361},{"heart_rate":97.0,"start_time":1724699726361},{"heart_rate":95.0,"start_time":1724699727361},{"heart_rate":92.0,"start_time":1724699728361},{"heart_rate":91.0,"start_time":1724699729361},{"heart_rate":91.0,"start_time":1724699730361},{"heart_rate":91.0,"start_time":1724699731361},{"heart_rate":92.0,"start_time":1724699732361},{"heart_rate":93.0,"start_time":1724699733361},{"heart_rate":94.0,"start_time":1724699734361},{"heart_rate":95.0,"start_time":1724699735361},{"heart_rate":97.0,"start_time":1724699736361},{"heart_rate":101.0,"start_time":1724699737361},{"heart_rate":104.0,"start_time":1724699738362},{"heart_rate":103.0,"start_time":1724699739362},{"heart_rate":103.0,"start_time":1724699740362},{"heart_rate":102.0,"start_time":1724699741362},{"heart_rate":102.0,"start_time":1724699742362},{"heart_rate":101.0,"start_time":1724699743362},{"heart_rate":101.0,"start_time":1724699744362},{"heart_rate":102.0,"start_time":1724699745362},{"heart_rate":103.0,"start_time":1724699746362},{"heart_rate":103.0,"start_time":1724699747362},{"heart_rate":103.0,"start_time":1724699748362},{"heart_rate":104.0,"start_time":1724699749362},{"heart_rate":105.0,"start_time":1724699750362},{"heart_rate":105.0,"start_time":1724699751362},{"heart_rate":105.0,"start_time":1724699752362},{"heart_rate":106.0,"start_time":1724699753362},{"heart_rate":107.0,"start_time":1724699754362},{"heart_rate":107.0,"start_time":1724699755362},{"heart_rate":108.0,"start_time":1724699756362},{"heart_rate":108.0,"start_time":1724699757362},{"heart_rate":107.0,"start_time":1724699758362},{"heart_rate":107.0,"start_time":1724699759361},{"heart_rate":107.0,"start_time":1724699760361},{"heart_rate":108.0,"start_time":1724699761361},{"heart_rate":108.0,"start_time":1724699762361},{"heart_rate":109.0,"start_time":1724699763361},{"heart_rate":109.0,"start_time":1724699764361},{"heart_rate":110.0,"start_time":1724699765361},{"heart_rate":110.0,"start_time":1724699766361},{"heart_rate":111.0,"start_time":1724699767361},{"heart_rate":113.0,"start_time":1724699768361},{"heart_rate":114.0,"start_time":1724699769361},{"heart_rate":114.0,"start_time":1724699770361},{"heart_rate":114.0,"start_time":1724699771361},{"heart_rate":115.0,"start_time":1724699772361},{"heart_rate":115.0,"start_time":1724699773361},{"heart_rate":115.0,"start_time":1724699774361},{"heart_rate":115.0,"start_time":1724699775361},{"heart_rate":115.0,"start_time":1724699776361},{"heart_rate":114.0,"start_time":1724699777361},{"heart_rate":114.0,"start_time":1724699778361},{"heart_rate":114.0,"start_time":1724699779361},{"heart_rate":114.0,"start_time":1724699780361},{"heart_rate":114.0,"start_time":1724699781361},{"heart_rate":115.0,"start_time":1724699782361},{"heart_rate":115.0,"start_time":1724699783361},{"heart_rate":116.0,"start_time":1724699784361},{"heart_rate":116.0,"start_time":1724699785361},{"heart_rate":117.0,"start_time":1724699786361},{"heart_rate":117.0,"start_time":1724699787361},{"heart_rate":117.0,"start_time":1724699788361},{"heart_rate":117.0,"start_time":1724699789361},{"heart_rate":116.0,"start_time":1724699790361},{"heart_rate":116.0,"start_time":1724699791361},{"heart_rate":116.0,"start_time":1724699792361},{"heart_rate":115.0,"start_time":1724699793361},{"heart_rate":114.0,"start_time":1724699794361},{"heart_rate":114.0,"start_time":1724699795361},{"heart_rate":113.0,"start_time":1724699796361},{"heart_rate":113.0,"start_time":1724699797361},{"heart_rate":112.0,"start_time":1724699798361},{"heart_rate":112.0,"start_time":1724699799361},{"heart_rate":111.0,"start_time":1724699800361},{"heart_rate":109.0,"start_time":1724699801361},{"heart_rate":108.0,"start_time":1724699802361},{"heart_rate":108.0,"start_time":1724699803361},{"heart_rate":108.0,"start_time":1724699804361},{"heart_rate":108.0,"start_time":1724699805361},{"heart_rate":108.0,"start_time":1724699806361},{"heart_rate":109.0,"start_time":1724699807361},{"heart_rate":109.0,"start_time":1724699808361},{"heart_rate":109.0,"start_time":1724699809361},{"heart_rate":109.0,"start_time":1724699810361},{"heart_rate":110.0,"start_time":1724699811361},{"heart_rate":110.0,"start_time":1724699812361},{"heart_rate":109.0,"start_time":1724699813361},{"heart_rate":108.0,"start_time":1724699814361},{"heart_rate":107.0,"start_time":1724699815361},{"heart_rate":108.0,"start_time":1724699816361},{"heart_rate":108.0,"start_time":1724699817361},{"heart_rate":108.0,"start_time":1724699818361},{"heart_rate":107.0,"start_time":1724699819361},{"heart_rate":108.0,"start_time":1724699820361},{"heart_rate":108.0,"start_time":1724699821361},{"heart_rate":109.0,"start_time":1724699822361},{"heart_rate":109.0,"start_time":1724699823361},{"heart_rate":109.0,"start_time":1724699824361},{"heart_rate":109.0,"start_time":1724699825361},{"heart_rate":109.0,"start_time":1724699826361},{"heart_rate":108.0,"start_time":1724699827361},{"heart_rate":108.0,"start_time":1724699828361},{"heart_rate":107.0,"start_time":1724699829361},{"heart_rate":107.0,"start_time":1724699830361},{"heart_rate":107.0,"start_time":1724699831361},{"heart_rate":106.0,"start_time":1724699832361},{"heart_rate":106.0,"start_time":1724699833361},{"heart_rate":106.0,"start_time":1724699834361},{"heart_rate":107.0,"start_time":1724699835361},{"heart_rate":107.0,"start_time":1724699836361},{"heart_rate":108.0,"start_time":1724699837361},{"heart_rate":108.0,"start_time":1724699838361},{"heart_rate":109.0,"start_time":1724699839361},{"heart_rate":110.0,"start_time":1724699840361},{"heart_rate":111.0,"start_time":1724699841361},{"heart_rate":111.0,"start_time":1724699842361},{"heart_rate":112.0,"start_time":1724699843361},{"heart_rate":112.0,"start_time":1724699844361},{"heart_rate":113.0,"start_time":1724699845361},{"heart_rate":113.0,"start_time":1724699846361},{"heart_rate":113.0,"start_time":1724699847361},{"heart_rate":113.0,"start_time":1724699848361},{"heart_rate":113.0,"start_time":1724699849361},{"heart_rate":113.0,"start_time":1724699850361},{"heart_rate":113.0,"start_time":1724699851361},{"heart_rate":113.0,"start_time":1724699852361},{"heart_rate":114.0,"start_time":1724699853361},{"heart_rate":115.0,"start_time":1724699854361},{"heart_rate":115.0,"start_time":1724699855361},{"heart_rate":115.0,"start_time":1724699856361},{"heart_rate":115.0,"start_time":1724699857361},{"heart_rate":115.0,"start_time":1724699858361},{"heart_rate":115.0,"start_time":1724699859361},{"heart_rate":115.0,"start_time":1724699860361},{"heart_rate":114.0,"start_time":1724699861361},{"heart_rate":114.0,"start_time":1724699862361},{"heart_rate":114.0,"start_time":1724699863361},{"heart_rate":113.0,"start_time":1724699864361},{"heart_rate":112.0,"start_time":1724699865361},{"heart_rate":111.0,"start_time":1724699866361},{"heart_rate":111.0,"start_time":1724699867361},{"heart_rate":110.0,"start_time":1724699868361},{"heart_rate":110.0,"start_time":1724699869361},{"heart_rate":110.0,"start_time":1724699870361},{"heart_rate":109.0,"start_time":1724699871361},{"heart_rate":108.0,"start_time":1724699872361},{"heart_rate":107.0,"start_time":1724699873361},{"heart_rate":106.0,"start_time":1724699874361},{"heart_rate":105.0,"start_time":1724699875361},{"heart_rate":104.0,"start_time":1724699876361},{"heart_rate":103.0,"start_time":1724699877361},{"heart_rate":102.0,"start_time":1724699878361},{"heart_rate":101.0,"start_time":1724699879361},{"heart_rate":101.0,"start_time":1724699880361},{"heart_rate":101.0,"start_time":1724699881361},{"heart_rate":102.0,"start_time":1724699882361},{"heart_rate":102.0,"start_time":1724699883361},{"heart_rate":102.0,"start_time":1724699884361},{"heart_rate":102.0,"start_time":1724699885361},{"heart_rate":102.0,"start_time":1724699886361},{"heart_rate":102.0,"start_time":1724699887361},{"heart_rate":102.0,"start_time":1724699888361},{"heart_rate":102.0,"start_time":1724699889361},{"heart_rate":102.0,"start_time":1724699890361},{"heart_rate":102.0,"start_time":1724699891361},{"heart_rate":102.0,"start_time":1724699892361},{"heart_rate":103.0,"start_time":1724699893361},{"heart_rate":103.0,"start_time":1724699894361},{"heart_rate":103.0,"start_time":1724699895361},{"heart_rate":103.0,"start_time":1724699896361},{"heart_rate":102.0,"start_time":1724699897361},{"heart_rate":101.0,"start_time":1724699898361},{"heart_rate":100.0,"start_time":1724699899361},{"heart_rate":100.0,"start_time":1724699900361},{"heart_rate":100.0,"start_time":1724699901361},{"heart_rate":99.0,"start_time":1724699902361},{"heart_rate":99.0,"start_time":1724699903361},{"heart_rate":99.0,"start_time":1724699904361},{"heart_rate":98.0,"start_time":1724699905361},{"heart_rate":96.0,"start_time":1724699906361},{"heart_rate":95.0,"start_time":1724699907361},{"heart_rate":95.0,"start_time":1724699908361},{"heart_rate":94.0,"start_time":1724699909361},{"heart_rate":94.0,"start_time":1724699910361},{"heart_rate":94.0,"start_time":1724699911361},{"heart_rate":94.0,"start_time":1724699912361},{"heart_rate":94.0,"start_time":1724699913361},{"heart_rate":94.0,"start_time":1724699914361},{"heart_rate":94.0,"start_time":1724699915361},{"heart_rate":94.0,"start_time":1724699916361},{"heart_rate":95.0,"start_time":1724699917361},{"heart_rate":96.0,"start_time":1724699918361},{"heart_rate":98.0,"start_time":1724699919361},{"heart_rate":100.0,"start_time":1724699920361},{"heart_rate":102.0,"start_time":1724699921361},{"heart_rate":103.0,"start_time":1724699922361},{"heart_rate":103.0,"start_time":1724699923361},{"heart_rate":104.0,"start_time":1724699924361},{"heart_rate":104.0,"start_time":1724699925361},{"heart_rate":105.0,"start_time":1724699926361},{"heart_rate":105.0,"start_time":1724699927361},{"heart_rate":106.0,"start_time":1724699928361},{"heart_rate":106.0,"start_time":1724699929361},{"heart_rate":108.0,"start_time":1724699930361},{"heart_rate":109.0,"start_time":1724699931361},{"heart_rate":110.0,"start_time":1724699932361},{"heart_rate":109.0,"start_time":1724699933361},{"heart_rate":109.0,"start_time":1724699934361},{"heart_rate":108.0,"start_time":1724699935361},{"heart_rate":108.0,"start_time":1724699936361},{"heart_rate":108.0,"start_time":1724699937361},{"heart_rate":108.0,"start_time":1724699938361},{"heart_rate":108.0,"start_time":1724699939361},{"heart_rate":108.0,"start_time":1724699940361},{"heart_rate":108.0,"start_time":1724699941361},{"heart_rate":108.0,"start_time":1724699942361},{"heart_rate":107.0,"start_time":1724699943361},{"heart_rate":100.0,"start_time":1724699944361},{"heart_rate":96.0,"start_time":1724699945361},{"heart_rate":96.0,"start_time":1724699946361},{"heart_rate":97.0,"start_time":1724699947361},{"heart_rate":97.0,"start_time":1724699948361},{"heart_rate":97.0,"start_time":1724699949361},{"heart_rate":95.0,"start_time":1724699950361},{"heart_rate":95.0,"start_time":1724699951361},{"heart_rate":96.0,"start_time":1724699952361},{"heart_rate":96.0,"start_time":1724699953361},{"heart_rate":97.0,"start_time":1724699954361},{"heart_rate":97.0,"start_time":1724699955361},{"heart_rate":98.0,"start_time":1724699956361},{"heart_rate":98.0,"start_time":1724699957361},{"heart_rate":99.0,"start_time":1724699958361},{"heart_rate":98.0,"start_time":1724699959361},{"heart_rate":99.0,"start_time":1724699960361},{"heart_rate":100.0,"start_time":1724699961361},{"heart_rate":100.0,"start_time":1724699962361},{"heart_rate":100.0,"start_time":1724699963361},{"heart_rate":101.0,"start_time":1724699964361},{"heart_rate":101.0,"start_time":1724699965361},{"heart_rate":102.0,"start_time":1724699966361},{"heart_rate":102.0,"start_time":1724699967361},{"heart_rate":103.0,"start_time":1724699968361},{"heart_rate":103.0,"start_time":1724699969361},{"heart_rate":103.0,"start_time":1724699970361},{"heart_rate":103.0,"start_time":1724699971361},{"heart_rate":103.0,"start_time":1724699972361},{"heart_rate":104.0,"start_time":1724699973361},{"heart_rate":104.0,"start_time":1724699974361},{"heart_rate":104.0,"start_time":1724699975361},{"heart_rate":105.0,"start_time":1724699976361},{"heart_rate":106.0,"start_time":1724699977361},{"heart_rate":107.0,"start_time":1724699978361},{"heart_rate":107.0,"start_time":1724699979361},{"heart_rate":107.0,"start_time":1724699980361},{"heart_rate":106.0,"start_time":1724699981361},{"heart_rate":104.0,"start_time":1724699982361},{"heart_rate":102.0,"start_time":1724699983361},{"heart_rate":100.0,"start_time":1724699984361},{"heart_rate":98.0,"start_time":1724699985361},{"heart_rate":96.0,"start_time":1724699986361},{"heart_rate":95.0,"start_time":1724699987361},{"heart_rate":93.0,"start_time":1724699988361},{"heart_rate":92.0,"start_time":1724699989361},{"heart_rate":91.0,"start_time":1724699990361},{"heart_rate":90.0,"start_time":1724699991361},{"heart_rate":90.0,"start_time":1724699992361},{"heart_rate":90.0,"start_time":1724699993361},{"heart_rate":91.0,"start_time":1724699994361},{"heart_rate":91.0,"start_time":1724699995361},{"heart_rate":91.0,"start_time":1724699996361},{"heart_rate":91.0,"start_time":1724699997361},{"heart_rate":91.0,"start_time":1724699998361},{"heart_rate":90.0,"start_time":1724699999361},{"heart_rate":89.0,"start_time":1724700000361},{"heart_rate":89.0,"start_time":1724700001361},{"heart_rate":89.0,"start_time":1724700002361},{"heart_rate":88.0,"start_time":1724700003361},{"heart_rate":86.0,"start_time":1724700004361},{"heart_rate":85.0,"start_time":1724700005361},{"heart_rate":84.0,"start_time":1724700006361},{"heart_rate":84.0,"start_time":1724700007361},{"heart_rate":83.0,"start_time":1724700008361},{"heart_rate":83.0,"start_time":1724700009361},{"heart_rate":83.0,"start_time":1724700010361},{"heart_rate":83.0,"start_time":1724700011361},{"heart_rate":84.0,"start_time":1724700012361},{"heart_rate":85.0,"start_time":1724700013361},{"heart_rate":85.0,"start_time":1724700014361},{"heart_rate":85.0,"start_time":1724700015361},{"heart_rate":85.0,"start_time":1724700016361},{"heart_rate":84.0,"start_time":1724700017361},{"heart_rate":84.0,"start_time":1724700018361},{"heart_rate":84.0,"start_time":1724700019361},{"heart_rate":85.0,"start_time":1724700020361},{"heart_rate":85.0,"start_time":1724700021361},{"heart_rate":86.0,"start_time":1724700022361},{"heart_rate":85.0,"start_time":1724700023361},{"heart_rate":85.0,"start_time":1724700024361},{"heart_rate":85.0,"start_time":1724700025361},{"heart_rate":84.0,"start_time":1724700026361},{"heart_rate":85.0,"start_time":1724700027361},{"heart_rate":85.0,"start_time":1724700028361},{"heart_rate":85.0,"start_time":1724700029361},{"heart_rate":84.0,"start_time":1724700030361},{"heart_rate":84.0,"start_time":1724700031361},{"heart_rate":83.0,"start_time":1724700032361},{"heart_rate":83.0,"start_time":1724700033361},{"heart_rate":83.0,"start_time":1724700034361},{"heart_rate":84.0,"start_time":1724700035361},{"heart_rate":84.0,"start_time":1724700036361},{"heart_rate":84.0,"start_time":1724700037361},{"heart_rate":84.0,"start_time":1724700038361},{"heart_rate":84.0,"start_time":1724700039361},{"heart_rate":83.0,"start_time":1724700040361},{"heart_rate":83.0,"start_time":1724700041361},{"heart_rate":82.0,"start_time":1724700042361},{"heart_rate":81.0,"start_time":1724700043361},{"heart_rate":80.0,"start_time":1724700044361},{"heart_rate":79.0,"start_time":1724700045361},{"heart_rate":79.0,"start_time":1724700046361},{"heart_rate":79.0,"start_time":1724700047361},{"heart_rate":79.0,"start_time":1724700048361},{"heart_rate":80.0,"start_time":1724700049361},{"heart_rate":81.0,"start_time":1724700050361},{"heart_rate":82.0,"start_time":1724700051361},{"heart_rate":83.0,"start_time":1724700052361},{"heart_rate":85.0,"start_time":1724700053361},{"heart_rate":87.0,"start_time":1724700054361},{"heart_rate":88.0,"start_time":1724700055361},{"heart_rate":88.0,"start_time":1724700056361},{"heart_rate":89.0,"start_time":1724700057361},{"heart_rate":89.0,"start_time":1724700058361},{"heart_rate":90.0,"start_time":1724700059361},{"heart_rate":90.0,"start_time":1724700060361},{"heart_rate":90.0,"start_time":1724700061361},{"heart_rate":90.0,"start_time":1724700062361},{"heart_rate":90.0,"start_time":1724700063361},{"heart_rate":90.0,"start_time":1724700064361},{"heart_rate":90.0,"start_time":1724700065361},{"heart_rate":91.0,"start_time":1724700066361},{"heart_rate":91.0,"start_time":1724700067361},{"heart_rate":91.0,"start_time":1724700068361},{"heart_rate":92.0,"start_time":1724700069361},{"heart_rate":92.0,"start_time":1724700070361},{"heart_rate":93.0,"start_time":1724700071361},{"heart_rate":94.0,"start_time":1724700072361},{"heart_rate":95.0,"start_time":1724700073361},{"heart_rate":96.0,"start_time":1724700074361},{"heart_rate":96.0,"start_time":1724700075361},{"heart_rate":97.0,"start_time":1724700076361},{"heart_rate":98.0,"start_time":1724700077361},{"heart_rate":99.0,"start_time":1724700078361},{"heart_rate":100.0,"start_time":1724700079361},{"heart_rate":101.0,"start_time":1724700080361},{"heart_rate":101.0,"start_time":1724700081361},{"heart_rate":102.0,"start_time":1724700082361},{"heart_rate":102.0,"start_time":1724700083361},{"heart_rate":102.0,"start_time":1724700084361},{"heart_rate":102.0,"start_time":1724700085361},{"heart_rate":102.0,"start_time":1724700086361},{"heart_rate":101.0,"start_time":1724700087361},{"heart_rate":101.0,"start_time":1724700088361},{"heart_rate":100.0,"start_time":1724700089361},{"heart_rate":100.0,"start_time":1724700090361},{"heart_rate":100.0,"start_time":1724700091361},{"heart_rate":100.0,"start_time":1724700092361},{"heart_rate":100.0,"start_time":1724700093361},{"heart_rate":99.0,"start_time":1724700094361},{"heart_rate":99.0,"start_time":1724700095361},{"heart_rate":99.0,"start_time":1724700096361},{"heart_rate":99.0,"start_time":1724700097361},{"heart_rate":99.0,"start_time":1724700098361},{"heart_rate":100.0,"start_time":1724700099361},{"heart_rate":100.0,"start_time":1724700100361},{"heart_rate":100.0,"start_time":1724700101361},{"heart_rate":100.0,"start_time":1724700102361},{"heart_rate":101.0,"start_time":1724700103361},{"heart_rate":101.0,"start_time":1724700104361},{"heart_rate":102.0,"start_time":1724700105361},{"heart_rate":104.0,"start_time":1724700106361},{"heart_rate":105.0,"start_time":1724700107361},{"heart_rate":105.0,"start_time":1724700108361},{"heart_rate":105.0,"start_time":1724700109361},{"heart_rate":105.0,"start_time":1724700110361},{"heart_rate":105.0,"start_time":1724700111361},{"heart_rate":105.0,"start_time":1724700112361},{"heart_rate":105.0,"start_time":1724700113361},{"heart_rate":105.0,"start_time":1724700114361},{"heart_rate":106.0,"start_time":1724700115361},{"heart_rate":106.0,"start_time":1724700116361},{"heart_rate":107.0,"start_time":1724700117361},{"heart_rate":107.0,"start_time":1724700118361},{"heart_rate":108.0,"start_time":1724700119361},{"heart_rate":108.0,"start_time":1724700120361},{"heart_rate":108.0,"start_time":1724700121361},{"heart_rate":108.0,"start_time":1724700122361},{"heart_rate":106.0,"start_time":1724700123361},{"heart_rate":105.0,"start_time":1724700124361},{"heart_rate":105.0,"start_time":1724700125361},{"heart_rate":106.0,"start_time":1724700126361},{"heart_rate":107.0,"start_time":1724700127361},{"heart_rate":108.0,"start_time":1724700128361},{"heart_rate":108.0,"start_time":1724700129361},{"heart_rate":109.0,"start_time":1724700130361},{"heart_rate":109.0,"start_time":1724700131361},{"heart_rate":110.0,"start_time":1724700132361},{"heart_rate":109.0,"start_time":1724700133362},{"heart_rate":110.0,"start_time":1724700134362},{"heart_rate":113.0,"start_time":1724700135362},{"heart_rate":113.0,"start_time":1724700136362},{"heart_rate":114.0,"start_time":1724700137362},{"heart_rate":114.0,"start_time":1724700138362},{"heart_rate":115.0,"start_time":1724700139362},{"heart_rate":115.0,"start_time":1724700140362},{"heart_rate":115.0,"start_time":1724700141362},{"heart_rate":114.0,"start_time":1724700142362},{"heart_rate":113.0,"start_time":1724700143362},{"heart_rate":112.0,"start_time":1724700144362},{"heart_rate":112.0,"start_time":1724700145362},{"heart_rate":113.0,"start_time":1724700146362},{"heart_rate":113.0,"start_time":1724700147362},{"heart_rate":113.0,"start_time":1724700148362},{"heart_rate":113.0,"start_time":1724700149362},{"heart_rate":113.0,"start_time":1724700150362},{"heart_rate":113.0,"start_time":1724700151362},{"heart_rate":114.0,"start_time":1724700152362},{"heart_rate":114.0,"start_time":1724700153362},{"heart_rate":114.0,"start_time":1724700154362},{"heart_rate":113.0,"start_time":1724700155362},{"heart_rate":113.0,"start_time":1724700156362},{"heart_rate":113.0,"start_time":1724700157362},{"heart_rate":113.0,"start_time":1724700158362},{"heart_rate":113.0,"start_time":1724700159362},{"heart_rate":114.0,"start_time":1724700160362},{"heart_rate":115.0,"start_time":1724700161362},{"heart_rate":115.0,"start_time":1724700162362},{"heart_rate":116.0,"start_time":1724700163362},{"heart_rate":116.0,"start_time":1724700164362},{"heart_rate":116.0,"start_time":1724700165362},{"heart_rate":116.0,"start_time":1724700166362},{"heart_rate":115.0,"start_time":1724700167362},{"heart_rate":115.0,"start_time":1724700168362},{"heart_rate":115.0,"start_time":1724700169362},{"heart_rate":115.0,"start_time":1724700170362},{"heart_rate":115.0,"start_time":1724700171362},{"heart_rate":114.0,"start_time":1724700172362},{"heart_rate":114.0,"start_time":1724700173362},{"heart_rate":113.0,"start_time":1724700174362},{"heart_rate":113.0,"start_time":1724700175362},{"heart_rate":112.0,"start_time":1724700176362},{"heart_rate":112.0,"start_time":1724700177362},{"heart_rate":112.0,"start_time":1724700178362},{"heart_rate":112.0,"start_time":1724700179362},{"heart_rate":112.0,"start_time":1724700180362},{"heart_rate":112.0,"start_time":1724700181362},{"heart_rate":112.0,"start_time":1724700182362},{"heart_rate":112.0,"start_time":1724700183362},{"heart_rate":112.0,"start_time":1724700184362},{"heart_rate":113.0,"start_time":1724700185362},{"heart_rate":113.0,"start_time":1724700186362},{"heart_rate":114.0,"start_time":1724700187362},{"heart_rate":115.0,"start_time":1724700188362},{"heart_rate":115.0,"start_time":1724700189362},{"heart_rate":115.0,"start_time":1724700190362},{"heart_rate":115.0,"start_time":1724700191362},{"heart_rate":115.0,"start_time":1724700192362},{"heart_rate":114.0,"start_time":1724700193362},{"heart_rate":113.0,"start_time":1724700194362},{"heart_rate":111.0,"start_time":1724700195362},{"heart_rate":110.0,"start_time":1724700196362},{"heart_rate":109.0,"start_time":1724700197362},{"heart_rate":107.0,"start_time":1724700198362},{"heart_rate":107.0,"start_time":1724700199362},{"heart_rate":106.0,"start_time":1724700200362},{"heart_rate":106.0,"start_time":1724700201362},{"heart_rate":106.0,"start_time":1724700202362},{"heart_rate":106.0,"start_time":1724700203362},{"heart_rate":107.0,"start_time":1724700204362},{"heart_rate":107.0,"start_time":1724700205362},{"heart_rate":108.0,"start_time":1724700206362},{"heart_rate":109.0,"start_time":1724700207361},{"heart_rate":109.0,"start_time":1724700208361},{"heart_rate":109.0,"start_time":1724700209361},{"heart_rate":109.0,"start_time":1724700210361},{"heart_rate":109.0,"start_time":1724700211361},{"heart_rate":110.0,"start_time":1724700212361},{"heart_rate":110.0,"start_time":1724700213361},{"heart_rate":111.0,"start_time":1724700214361},{"heart_rate":110.0,"start_time":1724700215361},{"heart_rate":109.0,"start_time":1724700216361},{"heart_rate":108.0,"start_time":1724700217361},{"heart_rate":107.0,"start_time":1724700218361},{"heart_rate":105.0,"start_time":1724700219361},{"heart_rate":105.0,"start_time":1724700220361},{"heart_rate":105.0,"start_time":1724700221361},{"heart_rate":105.0,"start_time":1724700222361},{"heart_rate":105.0,"start_time":1724700223361},{"heart_rate":106.0,"start_time":1724700224361},{"heart_rate":106.0,"start_time":1724700225361},{"heart_rate":107.0,"start_time":1724700226361},{"heart_rate":108.0,"start_time":1724700227361},{"heart_rate":108.0,"start_time":1724700228361},{"heart_rate":109.0,"start_time":1724700229361},{"heart_rate":109.0,"start_time":1724700230361},{"heart_rate":110.0,"start_time":1724700231361},{"heart_rate":110.0,"start_time":1724700232361},{"heart_rate":111.0,"start_time":1724700233361},{"heart_rate":111.0,"start_time":1724700234361},{"heart_rate":111.0,"start_time":1724700235361},{"heart_rate":111.0,"start_time":1724700236361},{"heart_rate":111.0,"start_time":1724700237361},{"heart_rate":112.0,"start_time":1724700238361},{"heart_rate":112.0,"start_time":1724700239361},{"heart_rate":112.0,"start_time":1724700240361},{"heart_rate":112.0,"start_time":1724700241361},{"heart_rate":112.0,"start_time":1724700242361},{"heart_rate":112.0,"start_time":1724700243361},{"heart_rate":113.0,"start_time":1724700244361},{"heart_rate":113.0,"start_time":1724700245361},{"heart_rate":113.0,"start_time":1724700246361},{"heart_rate":113.0,"start_time":1724700247361},{"heart_rate":114.0,"start_time":1724700248361},{"heart_rate":114.0,"start_time":1724700249361},{"heart_rate":115.0,"start_time":1724700250361},{"heart_rate":116.0,"start_time":1724700251465},{"heart_rate":117.0,"start_time":1724700254125},{"heart_rate":117.0,"start_time":1724700255125},{"heart_rate":118.0,"start_time":1724700256125},{"heart_rate":118.0,"start_time":1724700257125},{"heart_rate":118.0,"start_time":1724700258125},{"heart_rate":118.0,"start_time":1724700259125},{"heart_rate":117.0,"start_time":1724700260125},{"heart_rate":117.0,"start_time":1724700261125},{"heart_rate":117.0,"start_time":1724700262125},{"heart_rate":118.0,"start_time":1724700263125},{"heart_rate":119.0,"start_time":1724700264125},{"heart_rate":119.0,"start_time":1724700265125},{"heart_rate":118.0,"start_time":1724700266125},{"heart_rate":117.0,"start_time":1724700267125},{"heart_rate":116.0,"start_time":1724700268125},{"heart_rate":119.0,"start_time":1724700269125},{"heart_rate":119.0,"start_time":1724700270125},{"heart_rate":119.0,"start_time":1724700271125},{"heart_rate":120.0,"start_time":1724700272125},{"heart_rate":120.0,"start_time":1724700273125},{"heart_rate":120.0,"start_time":1724700274125},{"heart_rate":120.0,"start_time":1724700275125},{"heart_rate":121.0,"start_time":1724700276125},{"heart_rate":122.0,"start_time":1724700277125},{"heart_rate":122.0,"start_time":1724700278125},{"heart_rate":122.0,"start_time":1724700279125},{"heart_rate":123.0,"start_time":1724700280125},{"heart_rate":123.0,"start_time":1724700281125},{"heart_rate":123.0,"start_time":1724700282125},{"heart_rate":123.0,"start_time":1724700283125},{"heart_rate":123.0,"start_time":1724700284125},{"heart_rate":122.0,"start_time":1724700285125},{"heart_rate":122.0,"start_time":1724700286125},{"heart_rate":122.0,"start_time":1724700287125},{"heart_rate":122.0,"start_time":1724700288125},{"heart_rate":122.0,"start_time":1724700289125},{"heart_rate":122.0,"start_time":1724700290125},{"heart_rate":122.0,"start_time":1724700291125},{"heart_rate":122.0,"start_time":1724700292125},{"heart_rate":123.0,"start_time":1724700293125},{"heart_rate":124.0,"start_time":1724700294125},{"heart_rate":123.0,"start_time":1724700295125},{"heart_rate":123.0,"start_time":1724700296125},{"heart_rate":123.0,"start_time":1724700297125},{"heart_rate":123.0,"start_time":1724700298125},{"heart_rate":124.0,"start_time":1724700299125},{"heart_rate":124.0,"start_time":1724700300125},{"heart_rate":124.0,"start_time":1724700301126},{"heart_rate":123.0,"start_time":1724700302126},{"heart_rate":123.0,"start_time":1724700303126},{"heart_rate":124.0,"start_time":1724700304126},{"heart_rate":124.0,"start_time":1724700305126},{"heart_rate":124.0,"start_time":1724700306126},{"heart_rate":124.0,"start_time":1724700307126},{"heart_rate":125.0,"start_time":1724700308126},{"heart_rate":125.0,"start_time":1724700309126},{"heart_rate":125.0,"start_time":1724700310126},{"heart_rate":125.0,"start_time":1724700311126},{"heart_rate":125.0,"start_time":1724700312126},{"heart_rate":124.0,"start_time":1724700313126},{"heart_rate":123.0,"start_time":1724700314126},{"heart_rate":122.0,"start_time":1724700315126},{"heart_rate":123.0,"start_time":1724700316126},{"heart_rate":123.0,"start_time":1724700317126},{"heart_rate":124.0,"start_time":1724700318126},{"heart_rate":124.0,"start_time":1724700319126},{"heart_rate":125.0,"start_time":1724700320126},{"heart_rate":126.0,"start_time":1724700321126},{"heart_rate":126.0,"start_time":1724700322126},{"heart_rate":126.0,"start_time":1724700323126},{"heart_rate":126.0,"start_time":1724700324126},{"heart_rate":126.0,"start_time":1724700325126},{"heart_rate":126.0,"start_time":1724700326126},{"heart_rate":127.0,"start_time":1724700327126},{"heart_rate":127.0,"start_time":1724700328126},{"heart_rate":130.0,"start_time":1724700329126},{"heart_rate":130.0,"start_time":1724700330126},{"heart_rate":129.0,"start_time":1724700331126},{"heart_rate":129.0,"start_time":1724700332126},{"heart_rate":129.0,"start_time":1724700333126},{"heart_rate":128.0,"start_time":1724700334126},{"heart_rate":128.0,"start_time":1724700335126},{"heart_rate":128.0,"start_time":1724700336126},{"heart_rate":126.0,"start_time":1724700337126},{"heart_rate":125.0,"start_time":1724700338126},{"heart_rate":124.0,"start_time":1724700339126},{"heart_rate":123.0,"start_time":1724700340126},{"heart_rate":122.0,"start_time":1724700341126},{"heart_rate":121.0,"start_time":1724700342126},{"heart_rate":121.0,"start_time":1724700343126},{"heart_rate":121.0,"start_time":1724700344126},{"heart_rate":122.0,"start_time":1724700345126},{"heart_rate":119.0,"start_time":1724700346126},{"heart_rate":119.0,"start_time":1724700347126},{"heart_rate":118.0,"start_time":1724700348126},{"heart_rate":118.0,"start_time":1724700349126},{"heart_rate":118.0,"start_time":1724700350126},{"heart_rate":119.0,"start_time":1724700351126},{"heart_rate":119.0,"start_time":1724700352126},{"heart_rate":120.0,"start_time":1724700353126},{"heart_rate":121.0,"start_time":1724700354126},{"heart_rate":121.0,"start_time":1724700355126},{"heart_rate":122.0,"start_time":1724700356126},{"heart_rate":123.0,"start_time":1724700357126},{"heart_rate":124.0,"start_time":1724700358126},{"heart_rate":126.0,"start_time":1724700359126},{"heart_rate":126.0,"start_time":1724700360126},{"heart_rate":127.0,"start_time":1724700361126},{"heart_rate":128.0,"start_time":1724700362126},{"heart_rate":128.0,"start_time":1724700363126},{"heart_rate":129.0,"start_time":1724700364126},{"heart_rate":129.0,"start_time":1724700365126},{"heart_rate":129.0,"start_time":1724700366126},{"heart_rate":129.0,"start_time":1724700367126},{"heart_rate":129.0,"start_time":1724700368126},{"heart_rate":129.0,"start_time":1724700369126},{"heart_rate":130.0,"start_time":1724700370126},{"heart_rate":130.0,"start_time":1724700371126},{"heart_rate":130.0,"start_time":1724700372126},{"heart_rate":130.0,"start_time":1724700373126},{"heart_rate":130.0,"start_time":1724700374126},{"heart_rate":131.0,"start_time":1724700375126},{"heart_rate":131.0,"start_time":1724700376126},{"heart_rate":131.0,"start_time":1724700377126},{"heart_rate":131.0,"start_time":1724700378125},{"heart_rate":130.0,"start_time":1724700379125},{"heart_rate":130.0,"start_time":1724700380125},{"heart_rate":129.0,"start_time":1724700381125},{"heart_rate":129.0,"start_time":1724700382125},{"heart_rate":129.0,"start_time":1724700383125},{"heart_rate":128.0,"start_time":1724700384125},{"heart_rate":127.0,"start_time":1724700385125},{"heart_rate":126.0,"start_time":1724700386125},{"heart_rate":125.0,"start_time":1724700387125},{"heart_rate":125.0,"start_time":1724700388125},{"heart_rate":125.0,"start_time":1724700389125},{"heart_rate":125.0,"start_time":1724700390125},{"heart_rate":125.0,"start_time":1724700391125},{"heart_rate":125.0,"start_time":1724700392125},{"heart_rate":124.0,"start_time":1724700393125},{"heart_rate":124.0,"start_time":1724700394125},{"heart_rate":124.0,"start_time":1724700395125},{"heart_rate":124.0,"start_time":1724700396125},{"heart_rate":124.0,"start_time":1724700397125},{"heart_rate":124.0,"start_time":1724700398125},{"heart_rate":124.0,"start_time":1724700399125},{"heart_rate":79.0,"start_time":1724700045361},{"heart_rate":124.0,"start_time":1724700400125},{"heart_rate":125.0,"start_time":1724700401125},{"heart_rate":125.0,"start_time":1724700402125},{"heart_rate":125.0,"start_time":1724700403125},{"heart_rate":124.0,"start_time":1724700404125},{"heart_rate":124.0,"start_time":1724700405125},{"heart_rate":124.0,"start_time":1724700406125},{"heart_rate":123.0,"start_time":1724700407125},{"heart_rate":123.0,"start_time":1724700408125},{"heart_rate":123.0,"start_time":1724700409125},{"heart_rate":122.0,"start_time":1724700410125},{"heart_rate":121.0,"start_time":1724700411125},{"heart_rate":121.0,"start_time":1724700412125},{"heart_rate":121.0,"start_time":1724700413125},{"heart_rate":123.0,"start_time":1724700414125},{"heart_rate":124.0,"start_time":1724700415125},{"heart_rate":125.0,"start_time":1724700416125},{"heart_rate":126.0,"start_time":1724700417125},{"heart_rate":127.0,"start_time":1724700418125},{"heart_rate":127.0,"start_time":1724700419125},{"heart_rate":127.0,"start_time":1724700420125},{"heart_rate":127.0,"start_time":1724700421125},{"heart_rate":127.0,"start_time":1724700422125},{"heart_rate":127.0,"start_time":1724700423125},{"heart_rate":126.0,"start_time":1724700424125},{"heart_rate":125.0,"start_time":1724700425125},{"heart_rate":124.0,"start_time":1724700426125},{"heart_rate":123.0,"start_time":1724700427125},{"heart_rate":123.0,"start_time":1724700428125},{"heart_rate":123.0,"start_time":1724700429125},{"heart_rate":123.0,"start_time":1724700430125},{"heart_rate":123.0,"start_time":1724700431125},{"heart_rate":123.0,"start_time":1724700432125},{"heart_rate":124.0,"start_time":1724700433125},{"heart_rate":125.0,"start_time":1724700434125},{"heart_rate":125.0,"start_time":1724700435125},{"heart_rate":125.0,"start_time":1724700436125},{"heart_rate":125.0,"start_time":1724700437125},{"heart_rate":125.0,"start_time":1724700438125},{"heart_rate":125.0,"start_time":1724700439125},{"heart_rate":126.0,"start_time":1724700440125},{"heart_rate":126.0,"start_time":1724700441125},{"heart_rate":125.0,"start_time":1724700442125},{"heart_rate":125.0,"start_time":1724700443125},{"heart_rate":124.0,"start_time":1724700444125},{"heart_rate":123.0,"start_time":1724700445125},{"heart_rate":123.0,"start_time":1724700446125},{"heart_rate":123.0,"start_time":1724700447125},{"heart_rate":122.0,"start_time":1724700448125},{"heart_rate":122.0,"start_time":1724700449125},{"heart_rate":121.0,"start_time":1724700450125},{"heart_rate":121.0,"start_time":1724700451125},{"heart_rate":120.0,"start_time":1724700452125},{"heart_rate":120.0,"start_time":1724700453125},{"heart_rate":120.0,"start_time":1724700454125},{"heart_rate":120.0,"start_time":1724700455125},{"heart_rate":121.0,"start_time":1724700456125},{"heart_rate":122.0,"start_time":1724700457125},{"heart_rate":122.0,"start_time":1724700458125},{"heart_rate":123.0,"start_time":1724700459125},{"heart_rate":124.0,"start_time":1724700460125},{"heart_rate":124.0,"start_time":1724700461125},{"heart_rate":125.0,"start_time":1724700462125},{"heart_rate":126.0,"start_time":1724700463125},{"heart_rate":126.0,"start_time":1724700464125},{"heart_rate":125.0,"start_time":1724700465125},{"heart_rate":125.0,"start_time":1724700466125},{"heart_rate":126.0,"start_time":1724700467125},{"heart_rate":126.0,"start_time":1724700468125},{"heart_rate":126.0,"start_time":1724700469125},{"heart_rate":126.0,"start_time":1724700470125},{"heart_rate":125.0,"start_time":1724700471125},{"heart_rate":125.0,"start_time":1724700472125},{"heart_rate":124.0,"start_time":1724700473125},{"heart_rate":123.0,"start_time":1724700474125},{"heart_rate":123.0,"start_time":1724700475125},{"heart_rate":122.0,"start_time":1724700476125},{"heart_rate":122.0,"start_time":1724700477125},{"heart_rate":123.0,"start_time":1724700478125},{"heart_rate":123.0,"start_time":1724700479125},{"heart_rate":123.0,"start_time":1724700480125},{"heart_rate":123.0,"start_time":1724700481125},{"heart_rate":124.0,"start_time":1724700482125},{"heart_rate":124.0,"start_time":1724700483125},{"heart_rate":125.0,"start_time":1724700484125},{"heart_rate":125.0,"start_time":1724700485125},{"heart_rate":126.0,"start_time":1724700486125},{"heart_rate":127.0,"start_time":1724700487125},{"heart_rate":127.0,"start_time":1724700488125},{"heart_rate":127.0,"start_time":1724700489125},{"heart_rate":127.0,"start_time":1724700490125},{"heart_rate":126.0,"start_time":1724700491125},{"heart_rate":127.0,"start_time":1724700492125},{"heart_rate":127.0,"start_time":1724700493125},{"heart_rate":127.0,"start_time":1724700494125},{"heart_rate":128.0,"start_time":1724700495125},{"heart_rate":129.0,"start_time":1724700496125},{"heart_rate":130.0,"start_time":1724700497125},{"heart_rate":130.0,"start_time":1724700498125},{"heart_rate":131.0,"start_time":1724700499125},{"heart_rate":130.0,"start_time":1724700500125},{"heart_rate":129.0,"start_time":1724700501125},{"heart_rate":128.0,"start_time":1724700502125},{"heart_rate":127.0,"start_time":1724700503125},{"heart_rate":126.0,"start_time":1724700504125},{"heart_rate":124.0,"start_time":1724700505125},{"heart_rate":121.0,"start_time":1724700506125},{"heart_rate":121.0,"start_time":1724700507125},{"heart_rate":121.0,"start_time":1724700508125},{"heart_rate":121.0,"start_time":1724700509125},{"heart_rate":120.0,"start_time":1724700510125},{"heart_rate":120.0,"start_time":1724700511125},{"heart_rate":120.0,"start_time":1724700512125},{"heart_rate":120.0,"start_time":1724700513125},{"heart_rate":120.0,"start_time":1724700514125},{"heart_rate":120.0,"start_time":1724700515125},{"heart_rate":120.0,"start_time":1724700516125},{"heart_rate":120.0,"start_time":1724700517125},{"heart_rate":120.0,"start_time":1724700518125},{"heart_rate":121.0,"start_time":1724700519125},{"heart_rate":121.0,"start_time":1724700520125},{"heart_rate":120.0,"start_time":1724700521125},{"heart_rate":120.0,"start_time":1724700522125},{"heart_rate":120.0,"start_time":1724700523125},{"heart_rate":120.0,"start_time":1724700524125},{"heart_rate":120.0,"start_time":1724700525125},{"heart_rate":120.0,"start_time":1724700526125},{"heart_rate":120.0,"start_time":1724700527125},{"heart_rate":120.0,"start_time":1724700528125},{"heart_rate":120.0,"start_time":1724700529125},{"heart_rate":120.0,"start_time":1724700530125},{"heart_rate":118.0,"start_time":1724700531125},{"heart_rate":119.0,"start_time":1724700532125},{"heart_rate":119.0,"start_time":1724700533125},{"heart_rate":118.0,"start_time":1724700534125},{"heart_rate":117.0,"start_time":1724700535125},{"heart_rate":117.0,"start_time":1724700536125},{"heart_rate":117.0,"start_time":1724700537125},{"heart_rate":118.0,"start_time":1724700538125},{"heart_rate":118.0,"start_time":1724700539125},{"heart_rate":117.0,"start_time":1724700540125},{"heart_rate":117.0,"start_time":1724700541125},{"heart_rate":117.0,"start_time":1724700542125},{"heart_rate":116.0,"start_time":1724700543125},{"heart_rate":116.0,"start_time":1724700544125},{"heart_rate":117.0,"start_time":1724700545125},{"heart_rate":117.0,"start_time":1724700546125},{"heart_rate":117.0,"start_time":1724700547125},{"heart_rate":117.0,"start_time":1724700548125},{"heart_rate":116.0,"start_time":1724700550125},{"heart_rate":116.0,"start_time":1724700551125},{"heart_rate":117.0,"start_time":1724700552125},{"heart_rate":117.0,"start_time":1724700553125},{"heart_rate":117.0,"start_time":1724700554125},{"heart_rate":118.0,"start_time":1724700556125},{"heart_rate":120.0,"start_time":1724700558125},{"heart_rate":122.0,"start_time":1724700559125},{"heart_rate":123.0,"start_time":1724700560125},{"heart_rate":125.0,"start_time":1724700561125},{"heart_rate":126.0,"start_time":1724700562125},{"heart_rate":127.0,"start_time":1724700563125},{"heart_rate":128.0,"start_time":1724700564125},{"heart_rate":130.0,"start_time":1724700565125},{"heart_rate":132.0,"start_time":1724700566125},{"heart_rate":133.0,"start_time":1724700567125},{"heart_rate":133.0,"start_time":1724700568125},{"heart_rate":134.0,"start_time":1724700569125},{"heart_rate":135.0,"start_time":1724700570125},{"heart_rate":136.0,"start_time":1724700571125},{"heart_rate":136.0,"start_time":1724700572125},{"heart_rate":137.0,"start_time":1724700573125},{"heart_rate":137.0,"start_time":1724700574125},{"heart_rate":137.0,"start_time":1724700575125},{"heart_rate":137.0,"start_time":1724700576125},{"heart_rate":137.0,"start_time":1724700577125},{"heart_rate":137.0,"start_time":1724700578125},{"heart_rate":138.0,"start_time":1724700579232}]